core_pro/GDrive.py
core_pro/GMail.py
core_pro/GSheet.py
core_pro/GSlide.py
core_pro/__init__.py
core_pro/aws.py
core_pro/config.py
core_pro/download_url.py
core_pro/gcloud.py
core_pro/json_ops.py
core_pro/oop_sql.py
core_pro/seatalk_bot.py
core_pro/ultilities.py
core_pro-0.0.164.dist-info/METADATA
core_pro-0.0.164.dist-info/WHEEL
core_pro-0.0.164.dist-info/licenses/LICENSE
core_pro-0.0.164.dist-info/RECORD
