Metadata-Version: 2.4
Name: core_pro
Version: 0.0.164
Summary: A utility package for data science
Project-URL: Homepage, https://github.com/kevinkhang2909/core_pro
Project-URL: Bug Tracker, https://github.com/kevinkhang2909/core_pro/issues
Author-email: Kevin Khang <kevinkhang2909@gmail.com>
License: Copyright (c) 2023 Kevin Khang
License-File: LICENSE
Keywords: api, google, aws
Classifier: License :: OSI Approved :: MIT License
Classifier: Operating System :: OS Independent
Classifier: Programming Language :: Python :: 3
Requires-Python: >=3.10
Requires-Dist: boto3==1.35.99
Requires-Dist: build
Requires-Dist: duckdb
Requires-Dist: func-timeout
Requires-Dist: google-api-python-client
Requires-Dist: google-auth-oauthlib
Requires-Dist: google-cloud-storage
Requires-Dist: httpx
Requires-Dist: jupyter
Requires-Dist: openpyxl
Requires-Dist: orjson
Requires-Dist: pandas
Requires-Dist: polars
Requires-Dist: psutil
Requires-Dist: pyarrow
Requires-Dist: requests-toolbelt
Requires-Dist: rich
Requires-Dist: sqlalchemy
Requires-Dist: tenacity
Requires-Dist: tqdm
Requires-Dist: trino
Requires-Dist: twine
